[
    {
        "name": "Car Reign",
        "desc": "Website of a car importer and seller named Car Reign. It includes user dashboard and admin control of all the components. This website is developed using the MERN Stack technology",
        "tech": [
            "React",
            "Express.js",
            "React-Router",
            "Node.js",
            "Material-UI",
            "MongoDB",
            "Firebase"
        ],
        "clientSide": "https://github.com/minhazul-ashim/car-reign-clientSide",
        "backSide": "https://github.com/minhazul-ashim/car-reign-serverSide",
        "preview": "https://carreign.netlify.app/",
        "img": "https://i.ibb.co/GkjZ2s8/Frame-1carreign.png"
    },
    {
        "name": "Travello",
        "desc": "Website of a travel agency and tour planner named Travello. It includes user and admin interaction of all the components. This website is developed using the MERN Stack technology",
        "tech": [
            "React",
            "Express.js",
            "React-Router",
            "Node.js",
            "MongoDB",
            "Firebase"
        ],
        "clientSide": "https://github.com/minhazul-ashim/travello",
        "backSide": "https://github.com/minhazul-ashim/travello-serverSide",
        "preview": "https://travellotours.netlify.app/",
        "img": "https://i.ibb.co/W5CHB20/travello.png"
    },
    {
        "name": "Medico",
        "desc": "Website of a health service provider named Medico. It includes user interaction and dynamic routing. This website is developed using and focusing React majorly",
        "tech": [
            "React",
            "React-Router",
            "React Bootstrap",
            "Firebase"
        ],
        "clientSide": "https://github.com/minhazul-ashim/medico-health",
        "preview": "https://medicohealth.netlify.app/",
        "img": "https://i.ibb.co/N9vZVv3/Group-7medico.png"
    },
    {
        "name": "Edu Palace",
        "desc": "Website of a education service provider. It includes user interaction. This website is developed using React majorly.",
        "tech": [
            "React",
            "React-Router",
            "React Bootstrap",
            "Firebase"
        ],
        "clientSide": "https://github.com/minhazul-ashim/edu-palace",
        "preview": "https://edu-palace.netlify.app/",
        "img": "https://i.ibb.co/2n2R2Ny/edupalace.png"
    },
    {
        "name": "Red Onion",
        "desc": "Website of a restaurant. It includes user interaction, cart and order placement functionalities. This website is developed using the MERN Stack technology",
        "tech": [
            "React",
            "React Bootstrap",
            "React-Router",
            "Firebase"
        ],
        "clientSide": "https://github.com/minhazul-ashim/red-onion",
        "preview": "https://carreign.netlify.app/",
        "img": "https://i.ibb.co/cN07GgX/redonion.png"
    }
]